MANIFEST.in
README.md
setup.py
pytmnd/__init__.py
pytmnd/main.py
pytmnd/ytmnd.py
pytmnd.egg-info/PKG-INFO
pytmnd.egg-info/SOURCES.txt
pytmnd.egg-info/dependency_links.txt
pytmnd.egg-info/entry_points.txt
pytmnd.egg-info/top_level.txt