Metadata-Version: 1.1
Name: pytmnd
Version: 1.0.1
Summary: YTMND site-opener
Home-page: https://github.com/MattCCS/Pytmnd
Author: Matt Cotton
Author-email: matthewcotton.cs@gmail.com
License: UNKNOWN
Platform: UNKNOWN
Classifier: Programming Language :: Python :: 3
